qpod/__init__.py
qpod/__main__.py
qpod/server_jupyter.py
qpod/server_main.py
qpod/util.py
qpod/base/__init__.py
qpod/base/handlers.py
qpod/base/etc/qpod_hub-jpserverextension.json
qpod/base/etc/qpod_hub-nbextension.json
qpod/base/etc/qpod_hub-nbserverextension.json
qpod/base/static/package.json
qpod/base/static/base/images/favicon.png
qpod/base/static/base/images/logo-code-server.svg
qpod/base/static/base/images/logo-jupyter.svg
qpod/base/static/base/images/logo-rshiny.svg
qpod/base/static/base/images/logo-rstudio.svg
qpod/base/static/base/images/logo-tensorflow.svg
qpod/base/static/components/.yarn-integrity
qpod/base/static/components/.bin/loose-envify
qpod/base/static/components/bootstrap/CHANGELOG.md
qpod/base/static/components/bootstrap/Gruntfile.js
qpod/base/static/components/bootstrap/LICENSE
qpod/base/static/components/bootstrap/README.md
qpod/base/static/components/bootstrap/package.json
qpod/base/static/components/bootstrap/dist/css/bootstrap-theme.css
qpod/base/static/components/bootstrap/dist/css/bootstrap-theme.css.map
qpod/base/static/components/bootstrap/dist/css/bootstrap-theme.min.css
qpod/base/static/components/bootstrap/dist/css/bootstrap-theme.min.css.map
qpod/base/static/components/bootstrap/dist/css/bootstrap.css
qpod/base/static/components/bootstrap/dist/css/bootstrap.css.map
qpod/base/static/components/bootstrap/dist/css/bootstrap.min.css
qpod/base/static/components/bootstrap/dist/css/bootstrap.min.css.map
qpod/base/static/components/bootstrap/dist/fonts/glyphicons-halflings-regular.eot
qpod/base/static/components/bootstrap/dist/fonts/glyphicons-halflings-regular.svg
qpod/base/static/components/bootstrap/dist/fonts/glyphicons-halflings-regular.ttf
qpod/base/static/components/bootstrap/dist/fonts/glyphicons-halflings-regular.woff
qpod/base/static/components/bootstrap/dist/fonts/glyphicons-halflings-regular.woff2
qpod/base/static/components/bootstrap/dist/js/bootstrap.js
qpod/base/static/components/bootstrap/dist/js/bootstrap.min.js
qpod_hub-2021.10.11.dist-info/LICENSE
qpod_hub-2021.10.11.dist-info/METADATA
qpod_hub-2021.10.11.dist-info/WHEEL
qpod_hub-2021.10.11.dist-info/entry_points.txt
qpod_hub-2021.10.11.dist-info/top_level.txt
qpod_hub-2021.10.11.dist-info/RECORD
