Metadata-Version: 2.1
Name: qpod-hub
Version: 2021.10.11
Summary: A hub portal UI and proxy service for QPod.
Home-page: https://github.com/QPod/qpod-hub
Author: QPod
Author-email: 45032326+QPod0@users.noreply.github.com
License: BSD
Platform: Linux
Platform: Mac OS X
Platform: Windows
Classifier: Intended Audience :: Developers
Classifier: Intended Audience :: System Administrators
Classifier: Intended Audience :: Science/Research
Classifier: Programming Language :: Python :: 3
Classifier: License :: OSI Approved :: BSD License
Classifier: Operating System :: OS Independent
License-File: LICENSE
Requires-Dist: jupyter-server-proxy
